poolcontrolpy/__init__.py
poolcontrolpy/exceptions.py
poolcontrolpy/poolcontrolpy.py
poolcontrolpy-0.0.0.dist-info/LICENSE
poolcontrolpy-0.0.0.dist-info/WHEEL
poolcontrolpy-0.0.0.dist-info/METADATA
poolcontrolpy-0.0.0.dist-info/RECORD
