Metadata-Version: 2.1
Name: poolcontrolpy
Version: 0.0.0
Summary: Package for accessing nodejs-poolController
License: MIT
Author: Kevin Robinson
Requires-Python: >=3.9,<4.0
Classifier: License :: OSI Approved :: MIT License
Classifier: Programming Language :: Python :: 3
Classifier: Programming Language :: Python :: 3.10
Classifier: Programming Language :: Python :: 3.9
Requires-Dist: aiohttp (>=3.8.1,<4.0.0)
Requires-Dist: asyncio (>=3.4.3,<4.0.0)
